Topsis/__init__.py
Topsis/__main__.py
Topsis_Divyam_102103142-1.1.2.dist-info/METADATA
Topsis_Divyam_102103142-1.1.2.dist-info/WHEEL
Topsis_Divyam_102103142-1.1.2.dist-info/entry_points.txt
Topsis_Divyam_102103142-1.1.2.dist-info/top_level.txt
Topsis_Divyam_102103142-1.1.2.dist-info/RECORD
