Metadata-Version: 2.1
Name: Topsis-Divyam-102103142
Version: 1.1.2
Summary: TOPSIS implementation by Divyam Malik
Home-page: https://github.com/divyam6969/topsis-divyam-102103142
Author: Divyam Malik
Author-email: divyammalik2003@gmail.com
License: MIT
Classifier: License :: OSI Approved :: MIT License
Classifier: Programming Language :: Python :: 3.6
Classifier: Programming Language :: Python :: 3.7
Classifier: Programming Language :: Python :: 3.8
Requires-Dist: numpy
Requires-Dist: pandas
